httpie_auth_store/__init__.py
httpie_auth_store/_auth.py
httpie_auth_store/_secret.py
httpie_auth_store/_store.py
httpie_auth_store-4.0.0.dist-info/METADATA
httpie_auth_store-4.0.0.dist-info/WHEEL
httpie_auth_store-4.0.0.dist-info/entry_points.txt
httpie_auth_store-4.0.0.dist-info/RECORD
