Metadata-Version: 2.1
Name: httpie-auth-store
Version: 4.0.0
Summary: HTTPie: one auth to rule them all!
Home-page: https://github.com/ikalnytskyi/httpie-auth-store
License: MIT
Keywords: httpie,auth,store,keychain,plugin,credential
Author: Ihor Kalnytskyi
Author-email: ihor@kalnytskyi.com
Requires-Python: >=3.8,<4.0
Classifier: License :: OSI Approved :: MIT License
Classifier: Programming Language :: Python :: 3
Classifier: Programming Language :: Python :: 3.8
Classifier: Programming Language :: Python :: 3.9
Classifier: Programming Language :: Python :: 3.10
Classifier: Programming Language :: Python :: 3.11
Classifier: Programming Language :: Python :: 3.12
Requires-Dist: httpie (>=3.1,<4.0)
Requires-Dist: keyring (>=23.5)
Project-URL: Repository, https://github.com/ikalnytskyi/httpie-auth-store
